Franko/__init__.py
Franko/decline.bundle.js
Franko/franko.py
Franko/validate.py
franko-25.5.12.dist-info/licenses/LICENSE
franko-25.5.12.dist-info/METADATA
franko-25.5.12.dist-info/WHEEL
franko-25.5.12.dist-info/top_level.txt
franko-25.5.12.dist-info/RECORD
