Metadata-Version: 2.4
Name: Franko
Version: 25.5.12
Summary: Project for declension of Ukrainian names
Author: Danila Aleksandrov
Author-email: danila.alexandrov24@gmail.com
License: MIT
Classifier: Intended Audience :: Developers
Classifier: Programming Language :: Python :: 3
Classifier: License :: OSI Approved :: MIT License
Classifier: Operating System :: OS Independent
Classifier: Topic :: Text Processing :: Linguistic
Requires-Python: >=3.10
License-File: LICENSE
Requires-Dist: setuptools>=61.0
Requires-Dist: wheel
Requires-Dist: pydantic
Provides-Extra: dev-deps
Requires-Dist: pytest; extra == "dev-deps"
Dynamic: author
Dynamic: author-email
Dynamic: classifier
Dynamic: description
Dynamic: description-content-type
Dynamic: license
Dynamic: license-file
Dynamic: provides-extra
Dynamic: requires-dist
Dynamic: requires-python
Dynamic: summary
